rhubarbe/.pylintrc
rhubarbe/__init__.py
rhubarbe/__main__.py
rhubarbe/action.py
rhubarbe/book.py
rhubarbe/collector.py
rhubarbe/config.py
rhubarbe/display.py
rhubarbe/display_curses.py
rhubarbe/frisbee.py
rhubarbe/frisbeed.py
rhubarbe/guessip.py
rhubarbe/imageloader.py
rhubarbe/imagesaver.py
rhubarbe/imagesrepo.py
rhubarbe/imagezip.py
rhubarbe/inventorynodes.py
rhubarbe/inventorypdus.py
rhubarbe/inventoryphones.py
rhubarbe/inventoryrelays.py
rhubarbe/lease.sh
rhubarbe/leases.py
rhubarbe/logger.py
rhubarbe/main.py
rhubarbe/node.py
rhubarbe/plcapiproxy.py
rhubarbe/selector.py
rhubarbe/singleton.py
rhubarbe/ssh.py
rhubarbe/telnet.py
rhubarbe/version.py
rhubarbe/api/relays.py
rhubarbe/config/inventory-nodes.json.template
rhubarbe/config/inventory-pdus.yaml.template
rhubarbe/config/inventory-phones.json.template
rhubarbe/config/inventory-relays.yaml.template
rhubarbe/config/rhubarbe.conf
rhubarbe/monitor/__init__.py
rhubarbe/monitor/accountsmanager.py
rhubarbe/monitor/leases.py
rhubarbe/monitor/loop.py
rhubarbe/monitor/nodes.py
rhubarbe/monitor/pdus.py
rhubarbe/monitor/phones.py
rhubarbe/monitor/reconnectable.py
rhubarbe/scripts/NOTES.md
rhubarbe/scripts/eaton
rhubarbe/scripts/raspberry
rhubarbe/scripts/relay-TT
rhubarbe/scripts/relay-lingering
rhubarbe/scripts/test-ping.py
rhubarbe-8.2.1.dist-info/METADATA
rhubarbe-8.2.1.dist-info/WHEEL
rhubarbe-8.2.1.dist-info/entry_points.txt
rhubarbe-8.2.1.dist-info/licenses/LICENSE
rhubarbe-8.2.1.dist-info/RECORD
