Metadata-Version: 2.4
Name: rhubarbe
Version: 8.2.1
Summary: Testbed Management Framework for R2Lab
Project-URL: Homepage, https://github.com/fit-r2lab/rhubarbe
Author-email: Thierry Parmentelat <thierry.parmentelat@inria.fr>
License: CC-BY-NC-4.0
License-File: LICENSE
Keywords: R2lab,networking,testbed,wireless
Requires-Python: >=3.10
Requires-Dist: aiohttp
Requires-Dist: asynciojobs
Requires-Dist: asyncssh
Requires-Dist: dataclass-wizard
Requires-Dist: fastapi[standard]
Requires-Dist: httpie
Requires-Dist: pandas
Requires-Dist: progressbar33
Requires-Dist: r2lab
Requires-Dist: telnetlib3
Requires-Dist: websockets>=14
Provides-Extra: mapdataframe
Requires-Dist: pandas; extra == 'mapdataframe'
Provides-Extra: tests
Requires-Dist: pytest; extra == 'tests'
